alma_cdk/openapix/__init__.py
alma_cdk/openapix/py.typed
alma_cdk/openapix/_jsii/__init__.py
alma_cdk/openapix/_jsii/openapix@0.0.50.jsii.tgz
alma_cdk.openapix-0.0.50.dist-info/LICENSE
alma_cdk.openapix-0.0.50.dist-info/METADATA
alma_cdk.openapix-0.0.50.dist-info/WHEEL
alma_cdk.openapix-0.0.50.dist-info/top_level.txt
alma_cdk.openapix-0.0.50.dist-info/RECORD
